positional_embeddings_pytorch/__init__.py
positional_embeddings_pytorch/base.py
positional_embeddings_pytorch/enformer.py
positional_embeddings_pytorch/learned.py
positional_embeddings_pytorch/sinusoidal.py
positional_embeddings_pytorch/t5.py
positional_embeddings_pytorch/transformer_xl.py
positional_embeddings_pytorch/tupe.py
positional_embeddings_pytorch/utils.py
positional_embeddings_pytorch-0.0.1.dist-info/WHEEL
positional_embeddings_pytorch-0.0.1.dist-info/METADATA
positional_embeddings_pytorch-0.0.1.dist-info/RECORD
